<report>
<name>
deleteSOAPRepository
</name>
<measurementUnit>
response time (msec)
</measurementUnit>
<parameterLabels>
<label>
load
</label>
</parameterLabels>
<data>
<iteration startTime="Wed Oct 16 21:57:42 BRT 2013" sequence="1" endTime="Wed Oct 16 21:57:46 BRT 2013">
<parameters>
<value>
150
</value>
</parameters>
<measurements>
<value>
458.0
</value>
<value>
262.0
</value>
<value>
275.0
</value>
<value>
281.0
</value>
<value>
392.0
</value>
<value>
298.0
</value>
<value>
179.0
</value>
<value>
317.0
</value>
<value>
325.0
</value>
<value>
333.0
</value>
</measurements>
</iteration>
<iteration startTime="Wed Oct 16 21:57:51 BRT 2013" sequence="2" endTime="Wed Oct 16 21:57:53 BRT 2013">
<parameters>
<value>
350.0
</value>
</parameters>
<measurements>
<value>
389.0
</value>
<value>
167.0
</value>
<value>
233.0
</value>
<value>
187.0
</value>
<value>
130.0
</value>
<value>
153.0
</value>
<value>
159.0
</value>
<value>
176.0
</value>
<value>
150.0
</value>
<value>
229.0
</value>
</measurements>
</iteration>
<iteration startTime="Wed Oct 16 21:57:57 BRT 2013" sequence="3" endTime="Wed Oct 16 21:57:58 BRT 2013">
<parameters>
<value>
550.0
</value>
</parameters>
<measurements>
<value>
319.0
</value>
<value>
80.0
</value>
<value>
83.0
</value>
<value>
94.0
</value>
<value>
108.0
</value>
<value>
170.0
</value>
<value>
201.0
</value>
<value>
73.0
</value>
<value>
131.0
</value>
<value>
141.0
</value>
</measurements>
</iteration>
<iteration startTime="Wed Oct 16 21:58:02 BRT 2013" sequence="4" endTime="Wed Oct 16 21:58:03 BRT 2013">
<parameters>
<value>
750.0
</value>
</parameters>
<measurements>
<value>
143.0
</value>
<value>
66.0
</value>
<value>
142.0
</value>
<value>
177.0
</value>
<value>
53.0
</value>
<value>
144.0
</value>
<value>
65.0
</value>
<value>
143.0
</value>
<value>
226.0
</value>
<value>
120.0
</value>
</measurements>
</iteration>
<iteration startTime="Wed Oct 16 21:58:06 BRT 2013" sequence="5" endTime="Wed Oct 16 21:58:07 BRT 2013">
<parameters>
<value>
950.0
</value>
</parameters>
<measurements>
<value>
97.0
</value>
<value>
156.0
</value>
<value>
67.0
</value>
<value>
117.0
</value>
<value>
55.0
</value>
<value>
82.0
</value>
<value>
126.0
</value>
<value>
84.0
</value>
<value>
179.0
</value>
<value>
78.0
</value>
</measurements>
</iteration>
<iteration startTime="Wed Oct 16 21:58:11 BRT 2013" sequence="6" endTime="Wed Oct 16 21:58:12 BRT 2013">
<parameters>
<value>
1150.0
</value>
</parameters>
<measurements>
<value>
168.0
</value>
<value>
143.0
</value>
<value>
154.0
</value>
<value>
75.0
</value>
<value>
115.0
</value>
<value>
70.0
</value>
<value>
124.0
</value>
<value>
68.0
</value>
<value>
123.0
</value>
<value>
71.0
</value>
</measurements>
</iteration>
<iteration startTime="Wed Oct 16 21:58:16 BRT 2013" sequence="7" endTime="Wed Oct 16 21:58:17 BRT 2013">
<parameters>
<value>
1350.0
</value>
</parameters>
<measurements>
<value>
252.0
</value>
<value>
207.0
</value>
<value>
166.0
</value>
<value>
60.0
</value>
<value>
157.0
</value>
<value>
65.0
</value>
<value>
70.0
</value>
<value>
140.0
</value>
<value>
65.0
</value>
<value>
169.0
</value>
</measurements>
</iteration>
<iteration startTime="Wed Oct 16 21:58:21 BRT 2013" sequence="8" endTime="Wed Oct 16 21:58:21 BRT 2013">
<parameters>
<value>
1550.0
</value>
</parameters>
<measurements>
<value>
158.0
</value>
<value>
52.0
</value>
<value>
82.0
</value>
<value>
116.0
</value>
<value>
50.0
</value>
<value>
123.0
</value>
<value>
50.0
</value>
<value>
112.0
</value>
<value>
70.0
</value>
<value>
132.0
</value>
</measurements>
</iteration>
<iteration startTime="Wed Oct 16 21:58:27 BRT 2013" sequence="9" endTime="Wed Oct 16 21:58:27 BRT 2013">
<parameters>
<value>
1750.0
</value>
</parameters>
<measurements>
<value>
154.0
</value>
<value>
65.0
</value>
<value>
86.0
</value>
<value>
129.0
</value>
<value>
49.0
</value>
<value>
60.0
</value>
<value>
118.0
</value>
<value>
351.0
</value>
<value>
145.0
</value>
<value>
74.0
</value>
</measurements>
</iteration>
<iteration startTime="Wed Oct 16 21:58:32 BRT 2013" sequence="10" endTime="Wed Oct 16 21:58:33 BRT 2013">
<parameters>
<value>
1950.0
</value>
</parameters>
<measurements>
<value>
104.0
</value>
<value>
57.0
</value>
<value>
447.0
</value>
<value>
84.0
</value>
<value>
56.0
</value>
<value>
49.0
</value>
<value>
77.0
</value>
<value>
73.0
</value>
<value>
67.0
</value>
<value>
76.0
</value>
</measurements>
</iteration>
</data>
</report>

<!--
Initial Value: 150
Linear Increase: 200
Number of errors of step 0: 0
Number of errors of step 1: 1
Number of errors of step 2: 3
Number of errors of step 3: 4
Number of errors of step 4: 4
Number of errors of step 5: 5
Number of errors of step 6: 6
Number of errors of step 7: 5
Number of errors of step 8: 6
Number of errors of step 9: 8
-->
